{
"commits": [
{
	"repository": "https://github.com/ReactiveX/RxJava",
	"sha1": "d35b3e7d8b5fd7b509ed5cb78937b29dbe240210",
	"url": "https://github.com/ReactiveX/RxJava/commit/d35b3e7d8b5fd7b509ed5cb78937b29dbe240210",
	"refactorings": [{
	"type": "Add Thrown Exception Type",
	"description": "Add Thrown Exception Type InterruptedException in method public testSubscribeWithScheduler1() : void from class rx.concurrency.TestSchedulers",
	"leftSideLocations": [{
		"filePath": "rxjava-core/src/test/java/rx/concurrency/TestSchedulers.java",
		"startLine": 183,
		"endLine": 218,
		"startColumn": 5,
		"endColumn": 6,
		"codeElementType": "METHOD_DECLARATION",
		"description": "original method declaration",
		"codeElement": "public testSubscribeWithScheduler1() : void"
}],
	"rightSideLocations": [{
		"filePath": "rxjava-core/src/test/java/rx/concurrency/TestSchedulers.java",
		"startLine": 190,
		"endLine": 190,
		"startColumn": 54,
		"endColumn": 74,
		"codeElementType": "TYPE",
		"description": "added thrown exception type",
		"codeElement": "InterruptedException"
}, {
		"filePath": "rxjava-core/src/test/java/rx/concurrency/TestSchedulers.java",
		"startLine": 189,
		"endLine": 246,
		"startColumn": 5,
		"endColumn": 6,
		"codeElementType": "METHOD_DECLARATION",
		"description": "method declaration with added thrown exception type",
		"codeElement": "public testSubscribeWithScheduler1() : void"
}]
}
]
}]
}